lemkpg/__init__.py
lemkpg/constants.py
lemkpg/exceptions.py
lemkpg/utils.py
lemkpg-1.2.dist-info/LICENSE
lemkpg-1.2.dist-info/METADATA
lemkpg-1.2.dist-info/WHEEL
lemkpg-1.2.dist-info/top_level.txt
lemkpg-1.2.dist-info/RECORD
