Metadata-Version: 2.1
Name: lemkpg
Version: 1.2
Summary: lemkpg package give simple API interface for quick access to PostgreSQL DB via async way
Home-page: https://github.com/Daniil-Kost/lemkpg
Author: Daniil Kostyshak
Author-email: lemk@ukr.net
License: MIT
Platform: UNKNOWN
Classifier: Programming Language :: Python :: 3
Classifier: License :: OSI Approved :: MIT License
Requires-Dist: aiopg
Requires-Dist: psycopg2
